slingshot/__init__.py
slingshot/exceptions.py
slingshot/indices_manager.py
slingshot-0.0.5.dist-info/DESCRIPTION.rst
slingshot-0.0.5.dist-info/METADATA
slingshot-0.0.5.dist-info/metadata.json
slingshot-0.0.5.dist-info/RECORD
slingshot-0.0.5.dist-info/top_level.txt
slingshot-0.0.5.dist-info/WHEEL
