Metadata-Version: 2.0
Name: slingshot
Version: 0.0.5
Summary: Index Migration for ElasticSearch
Home-page: https://github.com/OohlaLabs/slingshot
Author: Thierry Jossermoz
Author-email: thierry.jossermoz@oohlalabs.com
License: MIT
Platform: UNKNOWN
Classifier: Development Status :: 3 - Alpha
Classifier: Environment :: Web Environment
Classifier: Intended Audience :: Developers
Classifier: Operating System :: OS Independent
Classifier: Programming Language :: Python
Classifier: Programming Language :: Python :: 2.7
Classifier: Programming Language :: Python :: 3.3
Classifier: Programming Language :: Python :: 3.4
Classifier: Topic :: Software Development :: Libraries :: Python Modules
Requires-Dist: elasticsearch (<2.0.0,>=1.6.0)
Requires-Dist: six (>=1.8.0)
